iwa/__init__.py
iwa/__main__.py
iwa/core/__init__.py
iwa/core/chainlist.py
iwa/core/cli.py
iwa/core/constants.py
iwa/core/db.py
iwa/core/http.py
iwa/core/ipfs.py
iwa/core/keys.py
iwa/core/mnemonic.py
iwa/core/models.py
iwa/core/monitor.py
iwa/core/plugins.py
iwa/core/pricing.py
iwa/core/rpc_monitor.py
iwa/core/secrets.py
iwa/core/tables.py
iwa/core/test.py
iwa/core/types.py
iwa/core/ui.py
iwa/core/utils.py
iwa/core/wallet.py
iwa/core/chain/__init__.py
iwa/core/chain/errors.py
iwa/core/chain/interface.py
iwa/core/chain/manager.py
iwa/core/chain/models.py
iwa/core/chain/rate_limiter.py
iwa/core/contracts/__init__.py
iwa/core/contracts/cache.py
iwa/core/contracts/contract.py
iwa/core/contracts/decoder.py
iwa/core/contracts/erc20.py
iwa/core/contracts/multisend.py
iwa/core/contracts/abis/erc20.json
iwa/core/contracts/abis/multisend.json
iwa/core/contracts/abis/multisend_call_only.json
iwa/core/services/__init__.py
iwa/core/services/account.py
iwa/core/services/balance.py
iwa/core/services/plugin.py
iwa/core/services/safe.py
iwa/core/services/safe_executor.py
iwa/core/services/transaction.py
iwa/core/services/transfer/__init__.py
iwa/core/services/transfer/base.py
iwa/core/services/transfer/erc20.py
iwa/core/services/transfer/multisend.py
iwa/core/services/transfer/native.py
iwa/core/services/transfer/swap.py
iwa/core/tests/test_gnosis_fee.py
iwa/core/tests/test_ipfs.py
iwa/core/tests/test_pricing.py
iwa/core/tests/test_regression_fixes.py
iwa/core/tests/test_wallet.py
iwa/plugins/__init__.py
iwa/plugins/gnosis/__init__.py
iwa/plugins/gnosis/cow_utils.py
iwa/plugins/gnosis/plugin.py
iwa/plugins/gnosis/safe.py
iwa/plugins/gnosis/cow/__init__.py
iwa/plugins/gnosis/cow/quotes.py
iwa/plugins/gnosis/cow/swap.py
iwa/plugins/gnosis/cow/types.py
iwa/plugins/gnosis/tests/test_cow.py
iwa/plugins/gnosis/tests/test_safe.py
iwa/plugins/olas/__init__.py
iwa/plugins/olas/constants.py
iwa/plugins/olas/events.py
iwa/plugins/olas/importer.py
iwa/plugins/olas/mech_reference.py
iwa-0.1.0.dist-info/licenses/LICENSE
iwa-0.1.0.dist-info/METADATA
iwa-0.1.0.dist-info/WHEEL
iwa-0.1.0.dist-info/entry_points.txt
iwa-0.1.0.dist-info/top_level.txt
iwa-0.1.0.dist-info/RECORD
