Metadata-Version: 2.4
Name: iwa
Version: 0.1.0
Summary: A secure, modular, and plugin-based framework for crypto agents and ops
Requires-Python: <4.0,>=3.12
License-File: LICENSE
Requires-Dist: bip-utils>=2.9.3
Requires-Dist: cryptography>=46.0.2
Requires-Dist: eth-account>=0.13.7
Requires-Dist: loguru>=0.7.3
Requires-Dist: pydantic>=2.12.0
Requires-Dist: pydantic-settings>=2.11.0
Requires-Dist: rich>=14.2.0
Requires-Dist: tomli>=2.3.0
Requires-Dist: tomli-w>=1.2.0
Requires-Dist: typer>=0.19.2
Requires-Dist: web3>=7.13.0
Requires-Dist: pyyaml<7.0.0,>=6.0.3
Requires-Dist: ruamel.yaml>=0.18.0
Requires-Dist: safe-eth-py>=7.14.0
Requires-Dist: twine>=6.2.0
Requires-Dist: cowdao-cowpy>=1.0.1
Requires-Dist: pytest>=9.0.1
Requires-Dist: textual>=0.47.1
Requires-Dist: pyperclip>=1.8.2
Requires-Dist: peewee>=3.17.0
Requires-Dist: fastapi>=0.115.0
Requires-Dist: uvicorn>=0.32.0
Requires-Dist: jinja2>=3.1.4
Requires-Dist: cbor2==5.8.0
Requires-Dist: slowapi>=0.1.9
Requires-Dist: nest-asyncio>=1.6.0
Requires-Dist: aiohttp>=3.13.3
Requires-Dist: pynacl>=1.6.2
Requires-Dist: urllib3>=2.6.3
Requires-Dist: multiformats>=0.3.1
Requires-Dist: requests>=2.32.0
Dynamic: license-file
